aiolang/__init__.py
aiolang/aiolang.py
aiolang/exceptions/__init__.py
aiolang/exceptions/exceptions.py
aiolang/language/__init__.py
aiolang/language/langs_text.py
aiolang/language/langs_voice.py
aiolang/language/langs_web.py
aiolang/methods/__init__.py
aiolang/methods/text_to_voice.py
aiolang/methods/translate_text.py
aiolang/network/__init__.py
aiolang/network/network.py
aiolang-0.0.3.dist-info/LICENSE
aiolang-0.0.3.dist-info/METADATA
aiolang-0.0.3.dist-info/WHEEL
aiolang-0.0.3.dist-info/top_level.txt
aiolang-0.0.3.dist-info/RECORD
