Metadata-Version: 2.1
Name: aiolang
Version: 0.0.3
Summary: Translate Google Framework For Python
Author: 
Author-email: aiolang.python@gmail.com
Keywords: python,translate
Classifier: Intended Audience :: Developers
Classifier: Programming Language :: Python :: 3
Classifier: Operating System :: Unix
Classifier: Operating System :: MacOS :: MacOS X
Classifier: Operating System :: Microsoft :: Windows
License-File: LICENSE
Requires-Dist: aiofiles
Requires-Dist: aiohttp
